fi/simulate/__init__.py
fi/simulate/agent/__init__.py
fi/simulate/agent/definition.py
fi/simulate/agent/wrapper.py
fi/simulate/agent/wrappers/__init__.py
fi/simulate/agent/wrappers/anthropic.py
fi/simulate/agent/wrappers/gemini.py
fi/simulate/agent/wrappers/langchain.py
fi/simulate/agent/wrappers/openai.py
fi/simulate/evaluation/__init__.py
fi/simulate/evaluation/ai_eval.py
fi/simulate/recording/__init__.py
fi/simulate/recording/room_recorder.py
fi/simulate/simulation/__init__.py
fi/simulate/simulation/engines/__init__.py
fi/simulate/simulation/engines/base.py
fi/simulate/simulation/engines/cloud.py
fi/simulate/simulation/engines/livekit.py
fi/simulate/simulation/generator.py
fi/simulate/simulation/models.py
fi/simulate/simulation/runner.py
fi/simulate/utils/routes.py
agent_simulate-0.1.2.dist-info/METADATA
agent_simulate-0.1.2.dist-info/WHEEL
agent_simulate-0.1.2.dist-info/RECORD
