Metadata-Version: 2.4
Name: agent-simulate
Version: 0.1.2
Summary: Voice AI agent simulator and evaluation harness
Author: Future AGI
Author-email: no-reply@futureagi.com
Requires-Python: >=3.10,<3.14
Classifier: Programming Language :: Python :: 3
Classifier: Programming Language :: Python :: 3.10
Classifier: Programming Language :: Python :: 3.11
Classifier: Programming Language :: Python :: 3.12
Classifier: Programming Language :: Python :: 3.13
Provides-Extra: all
Provides-Extra: evaluation
Provides-Extra: livekit
Requires-Dist: ai-evaluation (>=0.2.1) ; extra == "evaluation" or extra == "all"
Requires-Dist: fi-instrumentation-otel (>=0.1.16)
Requires-Dist: httpx (>=0.24.0)
Requires-Dist: livekit-agents[openai,silero] (>=1.2) ; extra == "livekit" or extra == "all"
Requires-Dist: numpy (>=1.26.0)
Requires-Dist: pandas (>=2.0.0)
Requires-Dist: python-dotenv (>=1.0.0)
